[
	{
		"month" : "1",
		"holiday" : {
			"date" : "1,2,3",
			"str" : ["BQCtest1"]
		},
		"status" : 1
	}, {
		"month" : "2",
		"holiday" : {
			"date" : "4,10,5",
			"str" : ["BQCtest2"]
		},
		"status" : 1
	}, {
		"month" : "3",
		"holiday" : {
			"date" : "",
			"str" : []
		},
		"status" : 0
	}, {
		"month" : "4",
		"holiday" : {
			"date" : "",
			"str" : []
		},
		"status" : 0
	}, {
		"month" : "5",
		"holiday" : {
			"date" : "",
			"str" : []
		},
		"status" : 0
	}, {
		"month" : "6",
		"holiday" : {
			"date" : "",
			"str" : []
		},
		"status" : 0
	}, {
		"month" : "7",
		"holiday" : {
			"date" : "",
			"str" : []
		},
		"status" : 0
	}, {
		"month" : "8",
		"holiday" : {
			"date" : "13,    25, 19",
			"str" : ["BQCtest8","BQCtest8","BQCtest8","BQCtest8"]
		},
		"status" : 0
	}, {
		"month" : "9",
		"holiday" : {
			"date" : "",
			"str" : []
		},
		"status" : 0
	}, {
		"month" : "10",
		"holiday" : {
			"date" : "",
			"str" : []
		},
		"status" : 0
	}, {
		"month" : "11",
		"holiday" : {
			"date" : "",
			"str" : []
		},
		"status" : 0
	}, {
		"month" : "12",
		"holiday" : {
			"date" : "15,20,31",
			"str" : ["BQCtest12", "BQCtest12"]
		},
		"status" : 1
	}
]