[
  {
    "term": "str_001",
    "definition": "Waiting for the permission of push message, then you can start to use QPlay.",
    "context": "",
    "term_plural": "",
    "reference": "",
    "comment": ""
  },
  {
    "term": "str_002",
    "definition": "活動報名e",
    "context": "",
    "term_plural": "",
    "reference": "",
    "comment": ""
  },
  {
    "term": "str_003",
    "definition": "報名記錄e",
    "context": "",
    "term_plural": "",
    "reference": "",
    "comment": ""
  },
  {
    "term": "str_004",
    "definition": "我的眷屬資料e",
    "context": "",
    "term_plural": "",
    "reference": "",
    "comment": ""
  },
  {
    "term": "str_005",
    "definition": "已開放：e",
    "context": "",
    "term_plural": "",
    "reference": "",
    "comment": ""
  },
  {
    "term": "str_006",
    "definition": "未來：e",
    "context": "",
    "term_plural": "",
    "reference": "",
    "comment": ""
  },
  {
    "term": "str_007",
    "definition": "開始報名e",
    "context": "",
    "term_plural": "",
    "reference": "",
    "comment": ""
  },
  {
    "term": "str_008",
    "definition": "報名管理e",
    "context": "",
    "term_plural": "",
    "reference": "",
    "comment": ""
  },
  {
    "term": "str_009",
    "definition": "取消報名e",
    "context": "",
    "term_plural": "",
    "reference": "",
    "comment": ""
  },
  {
    "term": "str_010",
    "definition": "更改資料e",
    "context": "",
    "term_plural": "",
    "reference": "",
    "comment": ""
  },
  {
    "term": "str_011",
    "definition": "確定送出e",
    "context": "",
    "term_plural": "",
    "reference": "",
    "comment": ""
  },
  {
    "term": "str_012",
    "definition": "選擇眷屬e",
    "context": "",
    "term_plural": "",
    "reference": "",
    "comment": ""
  },
  {
    "term": "str_013",
    "definition": "送出名單e",
    "context": "",
    "term_plural": "",
    "reference": "",
    "comment": ""
  },
  {
    "term": "str_014",
    "definition": "新增名單e",
    "context": "",
    "term_plural": "",
    "reference": "",
    "comment": ""
  },
  {
    "term": "str_015",
    "definition": "我要報名e",
    "context": "",
    "term_plural": "",
    "reference": "",
    "comment": ""
  },
  {
    "term": "str_016",
    "definition": "儲存e",
    "context": "",
    "term_plural": "",
    "reference": "",
    "comment": ""
  },
  {
    "term": "str_017",
    "definition": "已完成報名e",
    "context": "",
    "term_plural": "",
    "reference": "",
    "comment": ""
  },
  {
    "term": "str_018",
    "definition": "已完成修改e",
    "context": "",
    "term_plural": "",
    "reference": "",
    "comment": ""
  },
  {
    "term": "str_019",
    "definition": "報名已取消e",
    "context": "",
    "term_plural": "",
    "reference": "",
    "comment": ""
  },
  {
    "term": "str_020",
    "definition": "目前活動名額已額滿e",
    "context": "",
    "term_plural": "",
    "reference": "",
    "comment": ""
  },
  {
    "term": "str_021",
    "definition": "您已報名其他場次e",
    "context": "",
    "term_plural": "",
    "reference": "",
    "comment": ""
  },
  {
    "term": "str_022",
    "definition": "報名未完成e",
    "context": "",
    "term_plural": "",
    "reference": "",
    "comment": ""
  },
  {
    "term": "str_023",
    "definition": "確定回到上一頁？e",
    "context": "",
    "term_plural": "",
    "reference": "",
    "comment": ""
  },
  {
    "term": "str_024",
    "definition": "很抱歉，您報名的人數超過剩餘名額，請重新報名e",
    "context": "",
    "term_plural": "",
    "reference": "",
    "comment": ""
  },
  {
    "term": "str_025",
    "definition": "很抱歉，您報名的組數超過剩餘名額，請重新報名e",
    "context": "",
    "term_plural": "",
    "reference": "",
    "comment": ""
  },
  {
    "term": "str_026",
    "definition": "連線失敗e",
    "context": "",
    "term_plural": "",
    "reference": "",
    "comment": ""
  },
  {
    "term": "str_027",
    "definition": "請確認網路連線e",
    "context": "",
    "term_plural": "",
    "reference": "",
    "comment": ""
  },
  {
    "term": "str_028",
    "definition": "爲讓福委會資源有效運用，非因公缺席者，每人將扣款活動成本費e",
    "context": "",
    "term_plural": "",
    "reference": "",
    "comment": ""
  },
  {
    "term": "str_029",
    "definition": "好，我知道了e",
    "context": "",
    "term_plural": "",
    "reference": "",
    "comment": ""
  },
  {
    "term": "str_030",
    "definition": "確定取消報名e",
    "context": "",
    "term_plural": "",
    "reference": "",
    "comment": ""
  },
  {
    "term": "str_031",
    "definition": "確定取消編輯？e",
    "context": "",
    "term_plural": "",
    "reference": "",
    "comment": ""
  },
  {
    "term": "str_032",
    "definition": "確定刪除眷屬資料？e",
    "context": "",
    "term_plural": "",
    "reference": "",
    "comment": ""
  },
  {
    "term": "str_033",
    "definition": "確定取消新增？e",
    "context": "",
    "term_plural": "",
    "reference": "",
    "comment": ""
  },
  {
    "term": "str_034",
    "definition": "目前沒有任何活動e",
    "context": "",
    "term_plural": "",
    "reference": "",
    "comment": ""
  },
  {
    "term": "str_035",
    "definition": "僅顯示尚未結束的報名記錄e",
    "context": "",
    "term_plural": "",
    "reference": "",
    "comment": ""
  },
  {
    "term": "str_036",
    "definition": "目前沒有眷屬資料e",
    "context": "",
    "term_plural": "",
    "reference": "",
    "comment": ""
  },
  {
    "term": "str_037",
    "definition": "活動尚未結束無法刪除e",
    "context": "",
    "term_plural": "",
    "reference": "",
    "comment": ""
  },
  {
    "term": "str_038",
    "definition": "查無員工資料e",
    "context": "",
    "term_plural": "",
    "reference": "",
    "comment": ""
  },
  {
    "term": "str_039",
    "definition": "查請重新搜索e",
    "context": "",
    "term_plural": "",
    "reference": "",
    "comment": ""
  },
  {
    "term": "str_040",
    "definition": "請選擇e",
    "context": "",
    "term_plural": "",
    "reference": "",
    "comment": ""
  },
  {
    "term": "str_041",
    "definition": "新增眷屬資料失敗e",
    "context": "",
    "term_plural": "",
    "reference": "",
    "comment": ""
  },
  {
    "term": "str_042",
    "definition": "更新眷屬資料失敗e",
    "context": "",
    "term_plural": "",
    "reference": "",
    "comment": ""
  },
  {
    "term": "str_043",
    "definition": "刪除眷屬資料失敗e",
    "context": "",
    "term_plural": "",
    "reference": "",
    "comment": ""
  },
  {
    "term": "str_044",
    "definition": "關閉e",
    "context": "",
    "term_plural": "",
    "reference": "",
    "comment": ""
  },
  {
    "term": "str_045",
    "definition": "取消e",
    "context": "",
    "term_plural": "",
    "reference": "",
    "comment": ""
  },
  {
    "term": "str_046",
    "definition": "不取消e",
    "context": "",
    "term_plural": "",
    "reference": "",
    "comment": ""
  },
  {
    "term": "str_047",
    "definition": "報名取消失敗e",
    "context": "",
    "term_plural": "",
    "reference": "",
    "comment": ""
  },
  {
    "term": "str_048",
    "definition": "身份證字號e",
    "context": "",
    "term_plural": "",
    "reference": "",
    "comment": ""
  },
  {
    "term": "str_049",
    "definition": "生日e",
    "context": "",
    "term_plural": "",
    "reference": "",
    "comment": ""
  }
]