[
  {
    "term": "str_001",
    "definition": "Waiting for the permission of push message, then you can start to use QPlay.",
    "context": "",
    "term_plural": "",
    "reference": "",
    "comment": ""
  },
  {
    "term": "str_002",
    "definition": "活動報名e",
    "context": "",
    "term_plural": "",
    "reference": "",
    "comment": ""
  },
  {
    "term": "str_003",
    "definition": "報名記錄e",
    "context": "",
    "term_plural": "",
    "reference": "",
    "comment": ""
  },
  {
    "term": "str_004",
    "definition": "我的眷屬資料e",
    "context": "",
    "term_plural": "",
    "reference": "",
    "comment": ""
  },
  {
    "term": "str_005",
    "definition": "已開放：e",
    "context": "",
    "term_plural": "",
    "reference": "",
    "comment": ""
  },
  {
    "term": "str_006",
    "definition": "未來：e",
    "context": "",
    "term_plural": "",
    "reference": "",
    "comment": ""
  }
]